foxtail_trainer_client/__init__.py
foxtail_trainer_client/api_client.py
foxtail_trainer_client/configuration.py
foxtail_trainer_client/exceptions.py
foxtail_trainer_client/model_utils.py
foxtail_trainer_client/rest.py
foxtail_trainer_client/api/__init__.py
foxtail_trainer_client/api/custom_metric_api.py
foxtail_trainer_client/api/data_set_chunk_api.py
foxtail_trainer_client/api/job_api.py
foxtail_trainer_client/api/ml_model_api.py
foxtail_trainer_client/api/ml_model_with_training_result_api.py
foxtail_trainer_client/api/prediction_task_api.py
foxtail_trainer_client/api/report_api.py
foxtail_trainer_client/api/training_config_api.py
foxtail_trainer_client/api/training_result_api.py
foxtail_trainer_client/api/worker_api.py
foxtail_trainer_client/apis/__init__.py
foxtail_trainer_client/model/__init__.py
foxtail_trainer_client/model/add_or_update_model_hyperparameter.py
foxtail_trainer_client/model/add_or_update_model_hyperparameter_in_job.py
foxtail_trainer_client/model/aggregated_metric_report_dto.py
foxtail_trainer_client/model/create_custom_metric_dto.py
foxtail_trainer_client/model/create_data_sets_sizes_dto.py
foxtail_trainer_client/model/create_job_command.py
foxtail_trainer_client/model/create_metric_dto.py
foxtail_trainer_client/model/create_ml_model_dto.py
foxtail_trainer_client/model/create_ml_models_command.py
foxtail_trainer_client/model/create_model_hyperparameter_dto.py
foxtail_trainer_client/model/create_prediction_task_command.py
foxtail_trainer_client/model/create_training_config_dto.py
foxtail_trainer_client/model/create_training_history_dto.py
foxtail_trainer_client/model/create_training_result_command.py
foxtail_trainer_client/model/create_training_result_dto.py
foxtail_trainer_client/model/created_job_dto.py
foxtail_trainer_client/model/created_ml_models_dto.py
foxtail_trainer_client/model/created_prediction_task_dto.py
foxtail_trainer_client/model/custom_metric_dto.py
foxtail_trainer_client/model/custom_model_hyperparameter_dto.py
foxtail_trainer_client-0.7.5.dist-info/METADATA
foxtail_trainer_client-0.7.5.dist-info/WHEEL
foxtail_trainer_client-0.7.5.dist-info/top_level.txt
foxtail_trainer_client-0.7.5.dist-info/RECORD
