Metadata-Version: 2.1
Name: foxtail-trainer-client
Version: 0.7.5
Summary: Foxtail Trainer
Home-page: 
Author: OpenAPI Generator community
Author-email: team@openapitools.org
Keywords: OpenAPI,OpenAPI-Generator,Foxtail Trainer
Requires-Python: >=3.6
Requires-Dist: urllib3 (>=1.25.3)
Requires-Dist: python-dateutil
